<image_bundle width="512" height="512" border="2" edge="2">
	<node_list>
		<node>
			<name>fire_080</name>
			<inset>0</inset>
			<image_width>128</image_width>
			<image_height>128</image_height>
			<offset_x>39</offset_x>
			<offset_y>3</offset_y>
			<rect_x>95</rect_x>
			<rect_y>85</rect_y>
			<rect_width>50</rect_width>
			<rect_height>112</rect_height>
		</node>
		<node>
			<name>fire_081</name>
			<inset>0</inset>
			<image_width>128</image_width>
			<image_height>128</image_height>
			<offset_x>40</offset_x>
			<offset_y>4</offset_y>
			<rect_x>261</rect_x>
			<rect_y>230</rect_y>
			<rect_width>49</rect_width>
			<rect_height>111</rect_height>
		</node>
		<node>
			<name>fire_082</name>
			<inset>0</inset>
			<image_width>128</image_width>
			<image_height>128</image_height>
			<offset_x>39</offset_x>
			<offset_y>4</offset_y>
			<rect_x>54</rect_x>
			<rect_y>199</rect_y>
			<rect_width>50</rect_width>
			<rect_height>111</rect_height>
		</node>
		<node>
			<name>fire_083</name>
			<inset>0</inset>
			<image_width>128</image_width>
			<image_height>128</image_height>
			<offset_x>40</offset_x>
			<offset_y>3</offset_y>
			<rect_x>2</rect_x>
			<rect_y>209</rect_y>
			<rect_width>49</rect_width>
			<rect_height>112</rect_height>
		</node>
		<node>
			<name>fire_084</name>
			<inset>0</inset>
			<image_width>128</image_width>
			<image_height>128</image_height>
			<offset_x>40</offset_x>
			<offset_y>3</offset_y>
			<rect_x>147</rect_x>
			<rect_y>85</rect_y>
			<rect_width>50</rect_width>
			<rect_height>112</rect_height>
		</node>
		<node>
			<name>fire_085</name>
			<inset>0</inset>
			<image_width>128</image_width>
			<image_height>128</image_height>
			<offset_x>39</offset_x>
			<offset_y>3</offset_y>
			<rect_x>261</rect_x>
			<rect_y>2</rect_y>
			<rect_width>51</rect_width>
			<rect_height>112</rect_height>
		</node>
		<node>
			<name>fire_086</name>
			<inset>0</inset>
			<image_width>128</image_width>
			<image_height>128</image_height>
			<offset_x>39</offset_x>
			<offset_y>3</offset_y>
			<rect_x>199</rect_x>
			<rect_y>85</rect_y>
			<rect_width>50</rect_width>
			<rect_height>112</rect_height>
		</node>
		<node>
			<name>fire_087</name>
			<inset>0</inset>
			<image_width>128</image_width>
			<image_height>128</image_height>
			<offset_x>39</offset_x>
			<offset_y>4</offset_y>
			<rect_x>106</rect_x>
			<rect_y>199</rect_y>
			<rect_width>50</rect_width>
			<rect_height>111</rect_height>
		</node>
		<node>
			<name>fire_088</name>
			<inset>0</inset>
			<image_width>128</image_width>
			<image_height>128</image_height>
			<offset_x>40</offset_x>
			<offset_y>3</offset_y>
			<rect_x>2</rect_x>
			<rect_y>95</rect_y>
			<rect_width>50</rect_width>
			<rect_height>112</rect_height>
		</node>
		<node>
			<name>fire_089</name>
			<inset>0</inset>
			<image_width>128</image_width>
			<image_height>128</image_height>
			<offset_x>40</offset_x>
			<offset_y>3</offset_y>
			<rect_x>314</rect_x>
			<rect_y>2</rect_y>
			<rect_width>51</rect_width>
			<rect_height>112</rect_height>
		</node>
		<node>
			<name>fire_090</name>
			<inset>0</inset>
			<image_width>128</image_width>
			<image_height>128</image_height>
			<offset_x>40</offset_x>
			<offset_y>3</offset_y>
			<rect_x>251</rect_x>
			<rect_y>116</rect_y>
			<rect_width>50</rect_width>
			<rect_height>112</rect_height>
		</node>
		<node>
			<name>fire_091</name>
			<inset>0</inset>
			<image_width>128</image_width>
			<image_height>128</image_height>
			<offset_x>39</offset_x>
			<offset_y>3</offset_y>
			<rect_x>367</rect_x>
			<rect_y>2</rect_y>
			<rect_width>51</rect_width>
			<rect_height>112</rect_height>
		</node>
		<node>
			<name>fire_092</name>
			<inset>0</inset>
			<image_width>128</image_width>
			<image_height>128</image_height>
			<offset_x>39</offset_x>
			<offset_y>4</offset_y>
			<rect_x>158</rect_x>
			<rect_y>199</rect_y>
			<rect_width>50</rect_width>
			<rect_height>111</rect_height>
		</node>
		<node>
			<name>fire_093</name>
			<inset>0</inset>
			<image_width>128</image_width>
			<image_height>128</image_height>
			<offset_x>40</offset_x>
			<offset_y>3</offset_y>
			<rect_x>303</rect_x>
			<rect_y>116</rect_y>
			<rect_width>50</rect_width>
			<rect_height>112</rect_height>
		</node>
		<node>
			<name>fire_094</name>
			<inset>0</inset>
			<image_width>128</image_width>
			<image_height>128</image_height>
			<offset_x>40</offset_x>
			<offset_y>2</offset_y>
			<rect_x>420</rect_x>
			<rect_y>2</rect_y>
			<rect_width>50</rect_width>
			<rect_height>113</rect_height>
		</node>
		<node>
			<name>fire_095</name>
			<inset>0</inset>
			<image_width>128</image_width>
			<image_height>128</image_height>
			<offset_x>40</offset_x>
			<offset_y>3</offset_y>
			<rect_x>355</rect_x>
			<rect_y>116</rect_y>
			<rect_width>50</rect_width>
			<rect_height>112</rect_height>
		</node>
		<node>
			<name>fire_096</name>
			<inset>0</inset>
			<image_width>128</image_width>
			<image_height>128</image_height>
			<offset_x>40</offset_x>
			<offset_y>3</offset_y>
			<rect_x>407</rect_x>
			<rect_y>117</rect_y>
			<rect_width>50</rect_width>
			<rect_height>112</rect_height>
		</node>
		<node>
			<name>fire_097</name>
			<inset>0</inset>
			<image_width>128</image_width>
			<image_height>128</image_height>
			<offset_x>40</offset_x>
			<offset_y>5</offset_y>
			<rect_x>363</rect_x>
			<rect_y>231</rect_y>
			<rect_width>49</rect_width>
			<rect_height>110</rect_height>
		</node>
		<node>
			<name>fire_098</name>
			<inset>0</inset>
			<image_width>128</image_width>
			<image_height>128</image_height>
			<offset_x>40</offset_x>
			<offset_y>4</offset_y>
			<rect_x>312</rect_x>
			<rect_y>230</rect_y>
			<rect_width>49</rect_width>
			<rect_height>111</rect_height>
		</node>
		<node>
			<name>fire_099</name>
			<inset>0</inset>
			<image_width>128</image_width>
			<image_height>128</image_height>
			<offset_x>40</offset_x>
			<offset_y>3</offset_y>
			<rect_x>210</rect_x>
			<rect_y>230</rect_y>
			<rect_width>49</rect_width>
			<rect_height>112</rect_height>
		</node>
		<node>
			<name>fire_100</name>
			<inset>0</inset>
			<image_width>128</image_width>
			<image_height>128</image_height>
			<offset_x>40</offset_x>
			<offset_y>3</offset_y>
			<rect_x>459</rect_x>
			<rect_y>117</rect_y>
			<rect_width>50</rect_width>
			<rect_height>112</rect_height>
		</node>
		<node>
			<name>joystick_knob</name>
			<inset>0</inset>
			<image_width>55</image_width>
			<image_height>55</image_height>
			<offset_x>2</offset_x>
			<offset_y>2</offset_y>
			<rect_x>414</rect_x>
			<rect_y>231</rect_y>
			<rect_width>51</rect_width>
			<rect_height>51</rect_height>
		</node>
		<node>
			<name>joystick_back</name>
			<inset>0</inset>
			<image_width>91</image_width>
			<image_height>91</image_height>
			<offset_x>0</offset_x>
			<offset_y>0</offset_y>
			<rect_x>2</rect_x>
			<rect_y>2</rect_y>
			<rect_width>91</rect_width>
			<rect_height>91</rect_height>
		</node>
		<node>
			<name>life_empty</name>
			<inset>0</inset>
			<image_width>21</image_width>
			<image_height>18</image_height>
			<offset_x>0</offset_x>
			<offset_y>0</offset_y>
			<rect_x>210</rect_x>
			<rect_y>199</rect_y>
			<rect_width>21</rect_width>
			<rect_height>18</rect_height>
		</node>
		<node>
			<name>life_full</name>
			<inset>0</inset>
			<image_width>21</image_width>
			<image_height>18</image_height>
			<offset_x>0</offset_x>
			<offset_y>0</offset_y>
			<rect_x>2</rect_x>
			<rect_y>323</rect_y>
			<rect_width>21</rect_width>
			<rect_height>18</rect_height>
		</node>
		<node>
			<name>button_attack</name>
			<inset>0</inset>
			<image_width>81</image_width>
			<image_height>81</image_height>
			<offset_x>0</offset_x>
			<offset_y>0</offset_y>
			<rect_x>95</rect_x>
			<rect_y>2</rect_y>
			<rect_width>81</rect_width>
			<rect_height>81</rect_height>
		</node>
		<node>
			<name>button_attack_down</name>
			<inset>0</inset>
			<image_width>81</image_width>
			<image_height>81</image_height>
			<offset_x>0</offset_x>
			<offset_y>0</offset_y>
			<rect_x>178</rect_x>
			<rect_y>2</rect_y>
			<rect_width>81</rect_width>
			<rect_height>81</rect_height>
		</node>
		<node>
			<name>button_pause</name>
			<inset>0</inset>
			<image_width>40</image_width>
			<image_height>40</image_height>
			<offset_x>3</offset_x>
			<offset_y>3</offset_y>
			<rect_x>472</rect_x>
			<rect_y>2</rect_y>
			<rect_width>34</rect_width>
			<rect_height>34</rect_height>
		</node>
		<node>
			<name>button_pause_down</name>
			<inset>0</inset>
			<image_width>40</image_width>
			<image_height>40</image_height>
			<offset_x>3</offset_x>
			<offset_y>3</offset_y>
			<rect_x>472</rect_x>
			<rect_y>38</rect_y>
			<rect_width>34</rect_width>
			<rect_height>34</rect_height>
		</node>
		<node>
			<name>font_score_0</name>
			<inset>0</inset>
			<image_width>18</image_width>
			<image_height>30</image_height>
			<offset_x>0</offset_x>
			<offset_y>4</offset_y>
			<rect_x>25</rect_x>
			<rect_y>323</rect_y>
			<rect_width>18</rect_width>
			<rect_height>21</rect_height>
		</node>
		<node>
			<name>font_score_1</name>
			<inset>0</inset>
			<image_width>11</image_width>
			<image_height>30</image_height>
			<offset_x>0</offset_x>
			<offset_y>4</offset_y>
			<rect_x>496</rect_x>
			<rect_y>231</rect_y>
			<rect_width>11</rect_width>
			<rect_height>20</rect_height>
		</node>
		<node>
			<name>font_score_2</name>
			<inset>0</inset>
			<image_width>16</image_width>
			<image_height>30</image_height>
			<offset_x>0</offset_x>
			<offset_y>4</offset_y>
			<rect_x>129</rect_x>
			<rect_y>385</rect_y>
			<rect_width>16</rect_width>
			<rect_height>20</rect_height>
		</node>
		<node>
			<name>font_score_3</name>
			<inset>0</inset>
			<image_width>15</image_width>
			<image_height>30</image_height>
			<offset_x>0</offset_x>
			<offset_y>4</offset_y>
			<rect_x>183</rect_x>
			<rect_y>385</rect_y>
			<rect_width>15</rect_width>
			<rect_height>20</rect_height>
		</node>
		<node>
			<name>font_score_4</name>
			<inset>0</inset>
			<image_width>16</image_width>
			<image_height>30</image_height>
			<offset_x>0</offset_x>
			<offset_y>4</offset_y>
			<rect_x>147</rect_x>
			<rect_y>385</rect_y>
			<rect_width>16</rect_width>
			<rect_height>20</rect_height>
		</node>
		<node>
			<name>font_score_5</name>
			<inset>0</inset>
			<image_width>15</image_width>
			<image_height>30</image_height>
			<offset_x>0</offset_x>
			<offset_y>4</offset_y>
			<rect_x>200</rect_x>
			<rect_y>385</rect_y>
			<rect_width>15</rect_width>
			<rect_height>20</rect_height>
		</node>
		<node>
			<name>font_score_6</name>
			<inset>0</inset>
			<image_width>16</image_width>
			<image_height>30</image_height>
			<offset_x>0</offset_x>
			<offset_y>4</offset_y>
			<rect_x>233</rect_x>
			<rect_y>199</rect_y>
			<rect_width>16</rect_width>
			<rect_height>21</rect_height>
		</node>
		<node>
			<name>font_score_7</name>
			<inset>0</inset>
			<image_width>16</image_width>
			<image_height>30</image_height>
			<offset_x>0</offset_x>
			<offset_y>4</offset_y>
			<rect_x>476</rect_x>
			<rect_y>384</rect_y>
			<rect_width>16</rect_width>
			<rect_height>21</rect_height>
		</node>
		<node>
			<name>font_score_8</name>
			<inset>0</inset>
			<image_width>16</image_width>
			<image_height>30</image_height>
			<offset_x>0</offset_x>
			<offset_y>4</offset_y>
			<rect_x>494</rect_x>
			<rect_y>384</rect_y>
			<rect_width>16</rect_width>
			<rect_height>21</rect_height>
		</node>
		<node>
			<name>font_score_9</name>
			<inset>0</inset>
			<image_width>16</image_width>
			<image_height>30</image_height>
			<offset_x>0</offset_x>
			<offset_y>4</offset_y>
			<rect_x>165</rect_x>
			<rect_y>385</rect_y>
			<rect_width>16</rect_width>
			<rect_height>20</rect_height>
		</node>
		<node>
			<name>font_score_46</name>
			<inset>0</inset>
			<image_width>9</image_width>
			<image_height>30</image_height>
			<offset_x>0</offset_x>
			<offset_y>15</offset_y>
			<rect_x>84</rect_x>
			<rect_y>95</rect_y>
			<rect_width>9</rect_width>
			<rect_height>10</rect_height>
		</node>
		<node>
			<name>font_score_58</name>
			<inset>0</inset>
			<image_width>10</image_width>
			<image_height>30</image_height>
			<offset_x>0</offset_x>
			<offset_y>8</offset_y>
			<rect_x>83</rect_x>
			<rect_y>131</rect_y>
			<rect_width>10</rect_width>
			<rect_height>17</rect_height>
		</node>
		<node>
			<name>font_gold_0</name>
			<inset>0</inset>
			<image_width>29</image_width>
			<image_height>35</image_height>
			<offset_x>0</offset_x>
			<offset_y>1</offset_y>
			<rect_x>472</rect_x>
			<rect_y>74</rect_y>
			<rect_width>29</rect_width>
			<rect_height>34</rect_height>
		</node>
		<node>
			<name>font_gold_1</name>
			<inset>0</inset>
			<image_width>19</image_width>
			<image_height>35</image_height>
			<offset_x>0</offset_x>
			<offset_y>1</offset_y>
			<rect_x>487</rect_x>
			<rect_y>267</rect_y>
			<rect_width>19</rect_width>
			<rect_height>34</rect_height>
		</node>
		<node>
			<name>font_gold_2</name>
			<inset>0</inset>
			<image_width>26</image_width>
			<image_height>35</image_height>
			<offset_x>0</offset_x>
			<offset_y>0</offset_y>
			<rect_x>480</rect_x>
			<rect_y>347</rect_y>
			<rect_width>26</rect_width>
			<rect_height>35</rect_height>
		</node>
		<node>
			<name>font_gold_3</name>
			<inset>0</inset>
			<image_width>25</image_width>
			<image_height>35</image_height>
			<offset_x>0</offset_x>
			<offset_y>1</offset_y>
			<rect_x>422</rect_x>
			<rect_y>361</rect_y>
			<rect_width>25</rect_width>
			<rect_height>33</rect_height>
		</node>
		<node>
			<name>font_gold_4</name>
			<inset>0</inset>
			<image_width>28</image_width>
			<image_height>35</image_height>
			<offset_x>0</offset_x>
			<offset_y>1</offset_y>
			<rect_x>54</rect_x>
			<rect_y>95</rect_y>
			<rect_width>28</rect_width>
			<rect_height>34</rect_height>
		</node>
		<node>
			<name>font_gold_5</name>
			<inset>0</inset>
			<image_width>25</image_width>
			<image_height>35</image_height>
			<offset_x>0</offset_x>
			<offset_y>1</offset_y>
			<rect_x>449</rect_x>
			<rect_y>361</rect_y>
			<rect_width>25</rect_width>
			<rect_height>33</rect_height>
		</node>
		<node>
			<name>font_gold_6</name>
			<inset>0</inset>
			<image_width>27</image_width>
			<image_height>35</image_height>
			<offset_x>0</offset_x>
			<offset_y>1</offset_y>
			<rect_x>54</rect_x>
			<rect_y>131</rect_y>
			<rect_width>27</rect_width>
			<rect_height>34</rect_height>
		</node>
		<node>
			<name>font_gold_7</name>
			<inset>0</inset>
			<image_width>26</image_width>
			<image_height>35</image_height>
			<offset_x>0</offset_x>
			<offset_y>1</offset_y>
			<rect_x>394</rect_x>
			<rect_y>361</rect_y>
			<rect_width>26</rect_width>
			<rect_height>34</rect_height>
		</node>
		<node>
			<name>font_gold_8</name>
			<inset>0</inset>
			<image_width>27</image_width>
			<image_height>35</image_height>
			<offset_x>0</offset_x>
			<offset_y>1</offset_y>
			<rect_x>467</rect_x>
			<rect_y>231</rect_y>
			<rect_width>27</rect_width>
			<rect_height>34</rect_height>
		</node>
		<node>
			<name>font_gold_9</name>
			<inset>0</inset>
			<image_width>27</image_width>
			<image_height>35</image_height>
			<offset_x>0</offset_x>
			<offset_y>1</offset_y>
			<rect_x>480</rect_x>
			<rect_y>311</rect_y>
			<rect_width>27</rect_width>
			<rect_height>34</rect_height>
		</node>
		<node>
			<name>font_gold_43</name>
			<inset>0</inset>
			<image_width>28</image_width>
			<image_height>35</image_height>
			<offset_x>0</offset_x>
			<offset_y>3</offset_y>
			<rect_x>54</rect_x>
			<rect_y>167</rect_y>
			<rect_width>28</rect_width>
			<rect_height>29</rect_height>
		</node>
		<node>
			<name>game_label_score</name>
			<inset>0</inset>
			<image_width>75</image_width>
			<image_height>30</image_height>
			<offset_x>9</offset_x>
			<offset_y>4</offset_y>
			<rect_x>414</rect_x>
			<rect_y>338</rect_y>
			<rect_width>64</rect_width>
			<rect_height>21</rect_height>
		</node>
		<node>
			<name>game_label_rings</name>
			<inset>0</inset>
			<image_width>75</image_width>
			<image_height>30</image_height>
			<offset_x>12</offset_x>
			<offset_y>4</offset_y>
			<rect_x>414</rect_x>
			<rect_y>311</rect_y>
			<rect_width>61</rect_width>
			<rect_height>25</rect_height>
		</node>
		<node>
			<name>game_label_height</name>
			<inset>0</inset>
			<image_width>75</image_width>
			<image_height>30</image_height>
			<offset_x>2</offset_x>
			<offset_y>4</offset_y>
			<rect_x>414</rect_x>
			<rect_y>284</rect_y>
			<rect_width>71</rect_width>
			<rect_height>25</rect_height>
		</node>
		<node>
			<name>praise_text_life_gain</name>
			<inset>0</inset>
			<image_width>125</image_width>
			<image_height>35</image_height>
			<offset_x>0</offset_x>
			<offset_y>0</offset_y>
			<rect_x>129</rect_x>
			<rect_y>349</rect_y>
			<rect_width>125</rect_width>
			<rect_height>34</rect_height>
		</node>
		<node>
			<name>praise_text_life_lose</name>
			<inset>0</inset>
			<image_width>122</image_width>
			<image_height>35</image_height>
			<offset_x>0</offset_x>
			<offset_y>0</offset_y>
			<rect_x>256</rect_x>
			<rect_y>380</rect_y>
			<rect_width>122</rect_width>
			<rect_height>34</rect_height>
		</node>
		<node>
			<name>praise_text_dodge</name>
			<inset>0</inset>
			<image_width>135</image_width>
			<image_height>35</image_height>
			<offset_x>2</offset_x>
			<offset_y>0</offset_y>
			<rect_x>261</rect_x>
			<rect_y>343</rect_y>
			<rect_width>131</rect_width>
			<rect_height>35</rect_height>
		</node>
		<node>
			<name>praise_text_absorb</name>
			<inset>0</inset>
			<image_width>155</image_width>
			<image_height>35</image_height>
			<offset_x>2</offset_x>
			<offset_y>0</offset_y>
			<rect_x>53</rect_x>
			<rect_y>312</rect_y>
			<rect_width>151</rect_width>
			<rect_height>35</rect_height>
		</node>
		<node>
			<name>praise_text_evade</name>
			<inset>0</inset>
			<image_width>127</image_width>
			<image_height>35</image_height>
			<offset_x>1</offset_x>
			<offset_y>0</offset_y>
			<rect_x>2</rect_x>
			<rect_y>349</rect_y>
			<rect_width>125</rect_width>
			<rect_height>35</rect_height>
		</node>
	</node_list>
</image_bundle>
